{
    "id": "e6b0babf",
    "name": "Workman's Boots",
    "brand": "e28b46eb",
    "categories": [
        "a0f21ff8/2d4bfa01"
    ],
    "description": "Workman's Boots. Canvas shaft, durable fowler shaped toe. Cowhide and cotton. Strong and heavy. Warrantied. ",
    "variations": [
        {
            "itemId": "4f949dbe",
            "costs": [
                {
                    "currencyHash": 2084597891,
                    "nameHash": -915411861,
                    "isFromPrice": false,
                    "price": 1400,
                    "quantity": 1,
                    "unlockEnums": [],
                    "unlockIds": []
                },
                {
                    "currencyHash": 773203532,
                    "nameHash": -570078785,
                    "isFromPrice": false,
                    "price": 100,
                    "quantity": 1,
                    "unlockEnums": [],
                    "unlockIds": []
                },
                {
                    "currencyHash": 2084597891,
                    "nameHash": 75922725,
                    "offerEnumHash": -339828109,
                    "isFromPrice": false,
                    "price": 700,
                    "quantity": 1,
                    "unlockEnums": [],
                    "unlockIds": []
                },
                {
                    "currencyHash": 0,
                    "nameHash": 866168015,
                    "rewardEnumHash": -146027,
                    "isFromPrice": false,
                    "price": 0,
                    "quantity": 1,
                    "unlockEnums": [],
                    "unlockIds": []
                }
            ]
        },
        {
            "itemId": "08af8ff5",
            "costs": [
                {
                    "currencyHash": 2084597891,
                    "nameHash": -915411861,
                    "isFromPrice": false,
                    "price": 1400,
                    "quantity": 1,
                    "unlockEnums": [],
                    "unlockIds": []
                },
                {
                    "currencyHash": 773203532,
                    "nameHash": -570078785,
                    "isFromPrice": false,
                    "price": 100,
                    "quantity": 1,
                    "unlockEnums": [],
                    "unlockIds": []
                },
                {
                    "currencyHash": 2084597891,
                    "nameHash": 75922725,
                    "offerEnumHash": -339828109,
                    "isFromPrice": false,
                    "price": 700,
                    "quantity": 1,
                    "unlockEnums": [],
                    "unlockIds": []
                },
                {
                    "currencyHash": 0,
                    "nameHash": 866168015,
                    "rewardEnumHash": -146027,
                    "isFromPrice": false,
                    "price": 0,
                    "quantity": 1,
                    "unlockEnums": [],
                    "unlockIds": []
                }
            ]
        },
        {
            "itemId": "16a02bd6",
            "costs": [
                {
                    "currencyHash": 2084597891,
                    "nameHash": -915411861,
                    "isFromPrice": false,
                    "price": 1400,
                    "quantity": 1,
                    "unlockEnums": [],
                    "unlockIds": []
                },
                {
                    "currencyHash": 773203532,
                    "nameHash": -570078785,
                    "isFromPrice": false,
                    "price": 100,
                    "quantity": 1,
                    "unlockEnums": [],
                    "unlockIds": []
                },
                {
                    "currencyHash": 2084597891,
                    "nameHash": 75922725,
                    "offerEnumHash": -339828109,
                    "isFromPrice": false,
                    "price": 700,
                    "quantity": 1,
                    "unlockEnums": [],
                    "unlockIds": []
                },
                {
                    "currencyHash": 0,
                    "nameHash": 866168015,
                    "rewardEnumHash": -146027,
                    "isFromPrice": false,
                    "price": 0,
                    "quantity": 1,
                    "unlockEnums": [],
                    "unlockIds": []
                }
            ]
        },
        {
            "itemId": "e3d5c642",
            "costs": [
                {
                    "currencyHash": 2084597891,
                    "nameHash": -915411861,
                    "isFromPrice": false,
                    "price": 1400,
                    "quantity": 1,
                    "unlockEnums": [],
                    "unlockIds": []
                },
                {
                    "currencyHash": 773203532,
                    "nameHash": -570078785,
                    "isFromPrice": false,
                    "price": 100,
                    "quantity": 1,
                    "unlockEnums": [],
                    "unlockIds": []
                },
                {
                    "currencyHash": 2084597891,
                    "nameHash": 75922725,
                    "offerEnumHash": -339828109,
                    "isFromPrice": false,
                    "price": 700,
                    "quantity": 1,
                    "unlockEnums": [],
                    "unlockIds": []
                },
                {
                    "currencyHash": 0,
                    "nameHash": 866168015,
                    "rewardEnumHash": -146027,
                    "isFromPrice": false,
                    "price": 0,
                    "quantity": 1,
                    "unlockEnums": [],
                    "unlockIds": []
                }
            ]
        },
        {
            "itemId": "f23362fd",
            "costs": [
                {
                    "currencyHash": 2084597891,
                    "nameHash": -915411861,
                    "isFromPrice": false,
                    "price": 1400,
                    "quantity": 1,
                    "unlockEnums": [],
                    "unlockIds": []
                },
                {
                    "currencyHash": 773203532,
                    "nameHash": -570078785,
                    "isFromPrice": false,
                    "price": 100,
                    "quantity": 1,
                    "unlockEnums": [],
                    "unlockIds": []
                },
                {
                    "currencyHash": 2084597891,
                    "nameHash": 75922725,
                    "offerEnumHash": -339828109,
                    "isFromPrice": false,
                    "price": 700,
                    "quantity": 1,
                    "unlockEnums": [],
                    "unlockIds": []
                },
                {
                    "currencyHash": 0,
                    "nameHash": 866168015,
                    "rewardEnumHash": -146027,
                    "isFromPrice": false,
                    "price": 0,
                    "quantity": 1,
                    "unlockEnums": [],
                    "unlockIds": []
                }
            ]
        },
        {
            "itemId": "e3bec610",
            "costs": [
                {
                    "currencyHash": 2084597891,
                    "nameHash": -915411861,
                    "isFromPrice": false,
                    "price": 1400,
                    "quantity": 1,
                    "unlockEnums": [],
                    "unlockIds": []
                },
                {
                    "currencyHash": 773203532,
                    "nameHash": -570078785,
                    "isFromPrice": false,
                    "price": 100,
                    "quantity": 1,
                    "unlockEnums": [],
                    "unlockIds": []
                },
                {
                    "currencyHash": 2084597891,
                    "nameHash": 75922725,
                    "offerEnumHash": -339828109,
                    "isFromPrice": false,
                    "price": 700,
                    "quantity": 1,
                    "unlockEnums": [],
                    "unlockIds": []
                },
                {
                    "currencyHash": 0,
                    "nameHash": 866168015,
                    "rewardEnumHash": -146027,
                    "isFromPrice": false,
                    "price": 0,
                    "quantity": 1,
                    "unlockEnums": [],
                    "unlockIds": []
                }
            ]
        },
        {
            "itemId": "f1fc628b",
            "costs": [
                {
                    "currencyHash": 2084597891,
                    "nameHash": -915411861,
                    "isFromPrice": false,
                    "price": 1400,
                    "quantity": 1,
                    "unlockEnums": [],
                    "unlockIds": []
                },
                {
                    "currencyHash": 773203532,
                    "nameHash": -570078785,
                    "isFromPrice": false,
                    "price": 100,
                    "quantity": 1,
                    "unlockEnums": [],
                    "unlockIds": []
                },
                {
                    "currencyHash": 2084597891,
                    "nameHash": 75922725,
                    "offerEnumHash": -339828109,
                    "isFromPrice": false,
                    "price": 700,
                    "quantity": 1,
                    "unlockEnums": [],
                    "unlockIds": []
                },
                {
                    "currencyHash": 0,
                    "nameHash": 866168015,
                    "rewardEnumHash": -146027,
                    "isFromPrice": false,
                    "price": 0,
                    "quantity": 1,
                    "unlockEnums": [],
                    "unlockIds": []
                }
            ]
        },
        {
            "itemId": "cf6d1d6d",
            "costs": [
                {
                    "currencyHash": 2084597891,
                    "nameHash": -915411861,
                    "isFromPrice": false,
                    "price": 1400,
                    "quantity": 1,
                    "unlockEnums": [],
                    "unlockIds": []
                },
                {
                    "currencyHash": 773203532,
                    "nameHash": -570078785,
                    "isFromPrice": false,
                    "price": 100,
                    "quantity": 1,
                    "unlockEnums": [],
                    "unlockIds": []
                },
                {
                    "currencyHash": 2084597891,
                    "nameHash": 75922725,
                    "offerEnumHash": -339828109,
                    "isFromPrice": false,
                    "price": 700,
                    "quantity": 1,
                    "unlockEnums": [],
                    "unlockIds": []
                },
                {
                    "currencyHash": 0,
                    "nameHash": 866168015,
                    "rewardEnumHash": -146027,
                    "isFromPrice": false,
                    "price": 0,
                    "quantity": 1,
                    "unlockEnums": [],
                    "unlockIds": []
                }
            ]
        },
        {
            "itemId": "dd7fb992",
            "costs": [
                {
                    "currencyHash": 2084597891,
                    "nameHash": -915411861,
                    "isFromPrice": false,
                    "price": 1400,
                    "quantity": 1,
                    "unlockEnums": [],
                    "unlockIds": []
                },
                {
                    "currencyHash": 773203532,
                    "nameHash": -570078785,
                    "isFromPrice": false,
                    "price": 100,
                    "quantity": 1,
                    "unlockEnums": [],
                    "unlockIds": []
                },
                {
                    "currencyHash": 2084597891,
                    "nameHash": 75922725,
                    "offerEnumHash": -339828109,
                    "isFromPrice": false,
                    "price": 700,
                    "quantity": 1,
                    "unlockEnums": [],
                    "unlockIds": []
                },
                {
                    "currencyHash": 0,
                    "nameHash": 866168015,
                    "rewardEnumHash": -146027,
                    "isFromPrice": false,
                    "price": 0,
                    "quantity": 1,
                    "unlockEnums": [],
                    "unlockIds": []
                }
            ]
        },
        {
            "itemId": "f278dc84",
            "costs": [
                {
                    "currencyHash": 2084597891,
                    "nameHash": -915411861,
                    "isFromPrice": false,
                    "price": 1400,
                    "quantity": 1,
                    "unlockEnums": [],
                    "unlockIds": []
                },
                {
                    "currencyHash": 773203532,
                    "nameHash": -570078785,
                    "isFromPrice": false,
                    "price": 100,
                    "quantity": 1,
                    "unlockEnums": [],
                    "unlockIds": []
                },
                {
                    "currencyHash": 2084597891,
                    "nameHash": 75922725,
                    "offerEnumHash": -339828109,
                    "isFromPrice": false,
                    "price": 700,
                    "quantity": 1,
                    "unlockEnums": [],
                    "unlockIds": []
                },
                {
                    "currencyHash": 0,
                    "nameHash": 866168015,
                    "rewardEnumHash": -146027,
                    "isFromPrice": false,
                    "price": 0,
                    "quantity": 1,
                    "unlockEnums": [],
                    "unlockIds": []
                }
            ]
        }
    ],
    "clothingVariations": [
        {
            "twHex": "2b39da06",
            "itemId": "4f949dbe",
            "enumHash": 725211654,
            "thumbnailUrl": "/global/catalog/rdr2/c3e9018c/7254b9c2e5291a131ad519f437153b684618b57a.png",
            "unlockRank": 1,
            "requirements": [],
            "tags": [
                -719175624,
                -133342564,
                -1410215654,
                -1529356747
            ]
        },
        {
            "twHex": "b186e69e",
            "itemId": "08af8ff5",
            "enumHash": -1316559202,
            "thumbnailUrl": "/global/catalog/rdr2/8cab1311/49d4cea17f915b1f62205a4126414a86b636c914.png",
            "unlockRank": 1,
            "requirements": [],
            "tags": [
                -719175624,
                -133342564,
                -1410215654,
                -1529356747
            ]
        },
        {
            "twHex": "7fd5033b",
            "itemId": "16a02bd6",
            "enumHash": 2144666427,
            "thumbnailUrl": "/global/catalog/rdr2/018dfcd5/a478cd3672e6322a7c42594fa99b82bed9acd994.png",
            "unlockRank": 1,
            "requirements": [],
            "tags": [
                -133342564,
                -1410215654,
                -1529356747
            ]
        },
        {
            "twHex": "960a2fa5",
            "itemId": "e3d5c642",
            "enumHash": -1777717339,
            "thumbnailUrl": "/global/catalog/rdr2/a826ca08/b07e350980c505fc2f2502b42c70739d52ffe241.png",
            "unlockRank": 1,
            "requirements": [],
            "tags": [
                -719175624,
                -133342564,
                -1410215654,
                -1529356747
            ]
        },
        {
            "twHex": "6860d453",
            "itemId": "f23362fd",
            "enumHash": 1751176275,
            "thumbnailUrl": "/global/catalog/rdr2/9ef1b79e/c825a53ec732c1301d712e3129813d56fb7f856a.png",
            "unlockRank": 1,
            "requirements": [],
            "tags": [
                -719175624,
                -133342564,
                -1410215654,
                -1529356747
            ]
        },
        {
            "twHex": "e60c5004",
            "itemId": "e3bec610",
            "enumHash": -435400700,
            "thumbnailUrl": "/global/catalog/rdr2/43e9818f/b3d2b1edffbb2fb3ce08e889f4996b5e5fb5b747.png",
            "unlockRank": 1,
            "requirements": [],
            "tags": [
                -719175624,
                -133342564,
                -1410215654,
                -1529356747
            ]
        },
        {
            "twHex": "17fb33e1",
            "itemId": "f1fc628b",
            "enumHash": 402338785,
            "thumbnailUrl": "/global/catalog/rdr2/b9306c1b/9409a323daa8d54ba735204a83174a9cd5a0347b.png",
            "unlockRank": 1,
            "requirements": [],
            "tags": [
                -719175624,
                -133342564,
                -1410215654,
                -1529356747
            ]
        },
        {
            "twHex": "cdc99f7f",
            "itemId": "cf6d1d6d",
            "enumHash": -842424449,
            "thumbnailUrl": "/global/catalog/rdr2/828b7ed2/f52ed3fb14a855b0a73c392bbe317bae52ee5d0f.png",
            "unlockRank": 1,
            "requirements": [],
            "tags": [
                -133342564,
                -1410215654,
                -1529356747
            ]
        },
        {
            "twHex": "fb7f7aea",
            "itemId": "dd7fb992",
            "enumHash": -75531542,
            "thumbnailUrl": "/global/catalog/rdr2/55ca2550/bac79c8c8e04e5f33195d6caa5f2bdede31118cb.png",
            "unlockRank": 1,
            "requirements": [],
            "tags": [
                -133342564,
                -1410215654,
                -1529356747
            ]
        },
        {
            "twHex": "5ee73c80",
            "itemId": "f278dc84",
            "enumHash": 1592212608,
            "thumbnailUrl": "/global/catalog/rdr2/62c9c29f/37fb27c16f19b3b0a771755bb40e47c7b5bc4611.png",
            "unlockRank": 1,
            "requirements": [],
            "tags": [
                -719175624,
                -133342564,
                -1410215654,
                -1529356747
            ]
        }
    ],
    "group": "CLOTHING",
    "images": [
        {
            "type": 0,
            "url": "/global/catalog/rdr2/7b882217/465b85b9b4031ed29d50003b8ef55ff179e4f668.png",
            "altText": ""
        },
        {
            "type": 1,
            "url": "/global/catalog/rdr2/7b882217/b1ccba2a46203aca289ad61f0340cd319c7724af.png",
            "altText": ""
        }
    ],
    "slots": [
        {
            "hash": -673000374,
            "quantity": 1
        }
    ]
}